django_historicalrecords_unleashed-1.3.1.dist-info/DESCRIPTION.rst
django_historicalrecords_unleashed-1.3.1.dist-info/METADATA
django_historicalrecords_unleashed-1.3.1.dist-info/RECORD
django_historicalrecords_unleashed-1.3.1.dist-info/WHEEL
django_historicalrecords_unleashed-1.3.1.dist-info/metadata.json
django_historicalrecords_unleashed-1.3.1.dist-info/top_level.txt
history/__init__.py
history/manager.py
history/models.py
history/utils.py
