Metadata-Version: 2.0
Name: django-historicalrecords-unleashed
Version: 1.3.1
Summary: Marty Alchin`s HistoricalRecords from the ProDjango book.
Home-page: https://github.com/vikingco/django-historicalrecords
Author: Unleashed NV
Author-email: operations@unleashed.be
License: BSD
Platform: UNKNOWN
Classifier: Development Status :: 5 - Production/Stable
Classifier: Intended Audience :: Developers
Classifier: License :: OSI Approved :: BSD License
Classifier: Operating System :: OS Independent
Classifier: Programming Language :: Python
Classifier: Framework :: Django
Classifier: Topic :: Software Development :: Libraries :: Python Modules
Requires-Dist: Django (>=1.2)
